django_myuser/__init__.py
django_myuser/adapters.py
django_myuser/admin.py
django_myuser/apps.py
django_myuser/audit_signals.py
django_myuser/audit_utils.py
django_myuser/celery.py
django_myuser/exporters.py
django_myuser/migrations/0001_initial.py
django_myuser/migrations/0002_auditlog.py
django_myuser/migrations/0003_add_dataexportfile_model.py
django_myuser/migrations/__init__.py
django_myuser/models.py
django_myuser/serializers.py
django_myuser/signals.py
django_myuser/social_views.py
django_myuser/tasks.py
django_myuser/templates/account/email/account_deletion.html
django_myuser/templates/account/email/account_deletion.txt
django_myuser/templates/account/email/data_export.html
django_myuser/templates/account/email/data_export.txt
django_myuser/templates/account/email/email_confirmation_message.html
django_myuser/templates/account/email/email_confirmation_message.txt
django_myuser/templates/account/email/email_confirmation_subject.txt
django_myuser/templates/account/email/email_confirmed.html
django_myuser/templates/account/email/email_confirmed.txt
django_myuser/templates/account/email/password_change_alert.html
django_myuser/templates/account/email/password_change_alert.txt
django_myuser/templates/account/email/password_change_alert_subject.txt
django_myuser/templates/account/email/password_reset_key_message.html
django_myuser/templates/account/email/password_reset_key_message.txt
django_myuser/templates/account/email/password_reset_key_subject.txt
django_myuser/templates/account/email/welcome_message.html
django_myuser/templates/account/email/welcome_message.txt
django_myuser/templates/socialaccount/email/social_account_connected.html
django_myuser/templates/socialaccount/email/social_account_connected.txt
django_myuser/templates/socialaccount/email/social_account_connected_subject.txt
django_myuser/throttles.py
django_myuser/urls.py
django_myuser/views.py
django_myuser-0.0.5.dist-info/METADATA
django_myuser-0.0.5.dist-info/WHEEL
django_myuser-0.0.5.dist-info/RECORD
