Metadata-Version: 2.3
Name: django-myuser
Version: 0.0.5
Summary: A comprehensive Django package for advanced user authentication, user data management
License: MIT
Keywords: django,authentication,jwt,social-auth,gdpr,user-management,rest-api,celery,audit-logging
Author: Sanjaya Subedi
Author-email: jangedoo@gmail.com
Requires-Python: >=3.11
Classifier: Development Status :: 4 - Beta
Classifier: Environment :: Web Environment
Classifier: Framework :: Django
Classifier: Framework :: Django :: 5.0
Classifier: Intended Audience :: Developers
Classifier: License :: OSI Approved :: MIT License
Classifier: Operating System :: OS Independent
Classifier: Programming Language :: Python
Classifier: Programming Language :: Python :: 3
Classifier: Programming Language :: Python :: 3.11
Classifier: Programming Language :: Python :: 3.12
Classifier: Topic :: Internet :: WWW/HTTP
Classifier: Topic :: Internet :: WWW/HTTP :: Dynamic Content
Classifier: Topic :: Security
Classifier: Topic :: Software Development :: Libraries :: Python Modules
Classifier: Topic :: System :: Systems Administration :: Authentication/Directory
Requires-Dist: celery (>=5.5.3,<6.0.0)
Requires-Dist: dj-rest-auth (>=7.0.1,<8.0.0)
Requires-Dist: django (>=5.0)
Requires-Dist: django-allauth (>=65.11.1,<66.0.0)
Requires-Dist: djangorestframework (>=3.16.1,<4.0.0)
Requires-Dist: djangorestframework-simplejwt[crypto] (>=5.5.1,<6.0.0)
Requires-Dist: redis (>=6.4.0,<7.0.0)
Requires-Dist: requests (>=2.32.5,<3.0.0)
